zTyp/__init__.py
zTyp/core.py
zTyp-1.0.1.dist-info/METADATA
zTyp-1.0.1.dist-info/WHEEL
zTyp-1.0.1.dist-info/top_level.txt
zTyp-1.0.1.dist-info/RECORD
