Metadata-Version: 2.1
Name: zTyp
Version: 1.0.1
Summary: very simple library for input handling, and collision detection.
Author: i rely on cache
Author-email: saba.kopaleishvili@outlook.com
License: MIT
Classifier: Programming Language :: Python :: 3
Classifier: License :: OSI Approved :: MIT License
Classifier: Operating System :: OS Independent
Requires-Python: >=3.6
